mongodb_bundle/__init__.py
mongodb_bundle/bundle.py
mongodb_bundle-2.1.0.dist-info/LICENSE
mongodb_bundle-2.1.0.dist-info/WHEEL
mongodb_bundle-2.1.0.dist-info/METADATA
mongodb_bundle-2.1.0.dist-info/RECORD
