Metadata-Version: 2.1
Name: mongodb-bundle
Version: 2.1.0
Summary: Mongodb support for applauncher
Author: Alvaro Garcia
Author-email: maxpowel@gmail.com
Requires-Python: >=3.6,<4.0
Classifier: Programming Language :: Python :: 3
Classifier: Programming Language :: Python :: 3.6
Classifier: Programming Language :: Python :: 3.7
Classifier: Programming Language :: Python :: 3.8
Classifier: Programming Language :: Python :: 3.9
Requires-Dist: applauncher (>=2.0.0,<3.0.0)
Requires-Dist: pymongo (>=3.11.3,<4.0.0)
